simt_fly_machines/__init__.py
simt_fly_machines/api.py
simt_fly_machines/cli.py
simt_fly_machines/logging.py
simt_fly_machines-0.2.3.dist-info/LICENSE
simt_fly_machines-0.2.3.dist-info/METADATA
simt_fly_machines-0.2.3.dist-info/WHEEL
simt_fly_machines-0.2.3.dist-info/entry_points.txt
simt_fly_machines-0.2.3.dist-info/RECORD
