Metadata-Version: 2.3
Name: simt-fly-machines
Version: 0.2.3
Summary: A python API to start, stop and list Fly.io machines
Author: Chris Hatch
Author-email: chris@cepro.energy
Requires-Python: >=3.13,<4.0
Classifier: Programming Language :: Python :: 3
Classifier: Programming Language :: Python :: 3.13
Requires-Dist: python-dotenv (==1.0.1)
Requires-Dist: requests (==2.32.4)
Requires-Dist: structlog (==24.4.0)
Requires-Dist: types-requests (==2.32.4.20250611)
